Metadata-Version: 2.1
Name: testproject1999
Version: 0.0.1
Summary: testproject1999
Author: shobrook
Author-email: shobrookj@gmail.com
